gechozen/__init__.py
gechozen/axmlparser.py
gechozen/axmlprinter.py
gechozen/bytecode.py
gechozen/stringblock.py
gechozen/typeconstants.py
gechozen-1.4.dist-info/LICENSE.txt
gechozen-1.4.dist-info/METADATA
gechozen-1.4.dist-info/WHEEL
gechozen-1.4.dist-info/top_level.txt
gechozen-1.4.dist-info/RECORD
